emmv/__init__.py
emmv-0.0.4.dist-info/LICENSE.txt
emmv-0.0.4.dist-info/METADATA
emmv-0.0.4.dist-info/WHEEL
emmv-0.0.4.dist-info/top_level.txt
emmv-0.0.4.dist-info/RECORD
