Metadata-Version: 2.1
Name: emmv
Version: 0.0.4
Summary: Metrics for unsupervised anomaly detection models
Home-page: https://github.com/christian-oleary/emmv
Author: Christian O'Leary
Author-email: cjjoleary@gmail.com
License: UNKNOWN
Platform: UNKNOWN
Classifier: Programming Language :: Python :: 3
Classifier: License :: OSI Approved :: MIT License
Classifier: Operating System :: OS Independent
Requires-Python: >=3.6
License-File: LICENSE.txt
Requires-Dist: numpy
Requires-Dist: pandas
Requires-Dist: setuptools
Requires-Dist: scikit-learn
